{
	"dungeon" :
	{
		"town" :
		{
			"guildSpells" :
			{
				// Level 1
				"bless" :					3,
				"bloodlust" : 				5,
				"cure" : 					5,
				"curse" : 					5,
				"dispel" : 					10,
				"haste" : 					10,
				"magicArrow" :				30,
				"protectFire" :				3,
				"protectWater" :			3,
				"shield" :					5,
				"slow" :					5,
				"stoneSkin" :				5,
				"summonBoat" :				5,
				"viewAir" :					3,
				"viewEarth" :				3,

				// Level 2
				"blind" :					4,
				"deathRipple" :				0,
				"disguise" :				2,
				"disruptingRay" :			6,
				"fireWall" :				4,
				"fortune" :					2,
				"iceBolt" :					6,
				"lightningBolt" :			50,
				"precision" :				6,
				"quicksand" :				4,
				"removeObstacle" :			4,
				"scuttleBoat" :				4,
				"visions" :					2,
				"weakness" :				4,

				// Level 3
				"airShield" :				4,
				"animateDead" :				0,
				"antiMagic" :				8,
				"destroyUndead" :			4,
				"earthquake" :				4,
				"fireball" :				16,
				"forceField" :				8,
				"forgetfulness" :			4,
				"frostRing" :				12,
				"hypnotize" :				8,
				"landMine" :				12,
				"mirth" :					4,
				"misfortune" :				4,
				"protectAir" :				2,
				"protectEarth" :			4,
				"teleport" :				8,

				//Level 4
				"armageddon" :				10,
				"berserk" :					5,
				"chainLightning" :			10,
				"clone" :					5,
				"counterstrike" :			5,
				"fireShield" :				5,
				"frenzy" :					5,
				"inferno" :					5,
				"meteorShower" :			10,
				"prayer" :					0,
				"resurrection" :			10,
				"slayer" :					5,
				"sorrow" :					5,
				"townPortal" :				10,
				"waterWalk" :				10,

				//level 5
				"dimensionDoor" :			16,
				"fly" :						12,
				"implosion" :				12,
				"magicMirror" :				12,
				"sacriffice" :				12,
				"summonAirElemental" :		0,
				"summonEarthElemental" :	12,
				"summonFireElemental" :		12,
				"summonWaterElemental" :	12,
			}
		}
	}
}
